MANIFEST.in
README.rst
ec3
setup.py
IM2/__init__.py
IM2/auth.py
IM2/radl/__init__.py
IM2/radl/radl.py
IM2/radl/radl_json.py
IM2/radl/radl_parse.py
IM2/radl/radl_schema.json
bash_completion/ec3
ec3_cli.egg-info/PKG-INFO
ec3_cli.egg-info/SOURCES.txt
ec3_cli.egg-info/dependency_links.txt
ec3_cli.egg-info/requires.txt
ec3_cli.egg-info/top_level.txt
templates/blcr.radl
templates/bowtie2.radl
templates/centos-ec2.radl
templates/chronos.radl
templates/ckptman.radl
templates/clues.radl
templates/clues2.radl
templates/consul.radl
templates/docker-compose.radl
templates/docker.radl
templates/epilog_controller
templates/escherichia_coli_genome.radl
templates/extra_hd.radl
templates/extract_proxy.py
templates/frontend-behind-wall.radl
templates/galaxy-declic-tool.radl
templates/galaxy-disseq-tool.radl
templates/galaxy-glxcc-tool.radl
templates/galaxy-tools.radl
templates/galaxy.radl
templates/gnuplot.radl
templates/hadoop.radl
templates/htcondor.radl
templates/im.radl
templates/is_cluster_ready
templates/jupyter.radl
templates/kubefaas.radl
templates/kubernetes.radl
templates/lemonade.radl
templates/marathon.radl
templates/maui.radl
templates/mesos.radl
templates/monasca.radl
templates/mrbayes.radl
templates/munge.radl
templates/myproxy.radl
templates/myproxy_ltos.radl
templates/namd.radl
templates/nfs.radl
templates/nomad.radl
templates/octave.radl
templates/openports.radl
templates/openvpn.radl
templates/ophidia.radl
templates/refresh_token.py
templates/refreshtoken.radl
templates/renew_proxy.py
templates/sge.radl
templates/slurm-repo.conf
templates/slurm-repo.radl
templates/slurm.conf
templates/slurm.radl
templates/spark.radl
templates/sudo-copy.radl
templates/swap-disk.radl
templates/swarm.radl
templates/test-slurm.radl
templates/test-torque.radl
templates/tomcat.radl
templates/torque.radl
templates/ubuntu-azure.radl
templates/ubuntu-ec2.radl
templates/ubuntu-fbw.radl
templates/ubuntu-gce.radl
templates/ubuntu-hybrid-spot-ec2.radl
templates/ubuntu-opennebula.radl
templates/ubuntu-openstack.radl
templates/ubuntu-vmrc.radl
templates/zookeeper.radl