Metadata-Version: 1.0
Name: ec3-cli
Version: 2.2.1
Summary: Tool to deploy virtual elastic clusters on the cloud.
Home-page: http://www.grycap.upv.es/ec3/
Author: Amanda Calatrava, Eloy Romero, Miguel Caballer
Author-email: UNKNOWN
License: Apache 2.0
Keywords: cloud cluster elasticity
Platform: UNKNOWN
